aws_info_helper/__init__.py
aws_info_helper/ec2.py
aws_info_helper/parameter_store.py
aws_info_helper/route53.py
aws_info_helper/s3.py
aws_info_helper/settings.ini
aws_info_helper/scripts/__init__.py
aws_info_helper/scripts/ec2_info.py
aws_info_helper/scripts/ec2_ssh_command.py
aws_info_helper/scripts/ec2_update_collection.py
aws_info_helper/scripts/route53_info.py
aws_info_helper/scripts/route53_update_collection.py
aws_info_helper/scripts/s3_update_collection.py
aws_info_helper-0.1.3.dist-info/LICENSE.txt
aws_info_helper-0.1.3.dist-info/METADATA
aws_info_helper-0.1.3.dist-info/WHEEL
aws_info_helper-0.1.3.dist-info/entry_points.txt
aws_info_helper-0.1.3.dist-info/top_level.txt
aws_info_helper-0.1.3.dist-info/RECORD
