Metadata-Version: 2.1
Name: aws-info-helper
Version: 0.1.3
Summary: Helpers for working with Boto3 output and AWS resources 
Home-page: https://github.com/kenjyco/aws-info-helper
Download-URL: https://github.com/kenjyco/aws-info-helper/tarball/v0.1.3
Author: Ken
Author-email: kenjyco@gmail.com
License: MIT
Keywords: aws,boto,ec2,s3,route53,cli,command-line,helper,kenjyco
Platform: UNKNOWN
Classifier: Development Status :: 3 - Alpha
Classifier: Environment :: Console
Classifier: Intended Audience :: Developers
Classifier: License :: OSI Approved :: MIT License
Classifier: Operating System :: MacOS :: MacOS X
Classifier: Operating System :: POSIX :: Linux
Classifier: Programming Language :: Python :: 3.5
Classifier: Programming Language :: Python
Classifier: Topic :: Software Development :: Libraries
Classifier: Topic :: Utilities
License-File: LICENSE.txt
Requires-Dist: bg-helper
Requires-Dist: boto3
Requires-Dist: click (>=6.0)
Requires-Dist: dt-helper
Requires-Dist: input-helper
Requires-Dist: settings-helper
Provides-Extra: redis-helper
Requires-Dist: redis-helper ; extra == 'redis-helper'
